mediafiredlpy/__init__.py
mediafiredlpy-0.1.2.dist-info/licenses/LICENSE
mediafiredlpy-0.1.2.dist-info/WHEEL
mediafiredlpy-0.1.2.dist-info/METADATA
mediafiredlpy-0.1.2.dist-info/RECORD
