Metadata-Version: 2.4
Name: mediafiredlpy
Version: 0.1.2
Summary: A simple Python module to extract Mediafire download links
Author-email: lasith ruwantha Amarwash <lalnishshanka3@gmail.com>
Requires-Python: >=3.6
License-Expression: MIT
License-File: LICENSE
Requires-Dist: beautifulsoup4==4.14.3
Requires-Dist: requests==2.32.5
